peppi_py-0.8.6.dist-info/METADATA
peppi_py-0.8.6.dist-info/WHEEL
peppi_py/__init__.py
peppi_py/_peppi.abi3.so
peppi_py/frame.py
peppi_py/game.py
peppi_py/parse.py
peppi_py/util.py
peppi_py-0.8.6.dist-info/RECORD
