Metadata-Version: 2.4
Name: peppi-py
Version: 0.8.6
Requires-Dist: pyarrow~=21.0
Requires-Dist: inflection~=0.5
Requires-Python: >=3.10
